pytdbot/__init__.py
pytdbot/client.py
pytdbot/filters.py
pytdbot/generate_files.py
pytdbot/generate_json.py
pytdbot/utils.py
pytdbot/exception/__init__.py
pytdbot/handlers/__init__.py
pytdbot/handlers/decorators.py
pytdbot/handlers/handler.py
pytdbot/handlers/updates.py
pytdbot/lib/libtdjson.so
pytdbot/methods/__init__.py
pytdbot/methods/methods.py
pytdbot/methods/tdlibfunctions.py
pytdbot/tdjson/__init__.py
pytdbot/tdjson/tdjson.py
pytdbot/types/__init__.py
pytdbot/types/buttons/__init__.py
pytdbot/types/buttons/base.py
pytdbot/types/buttons/force_reply.py
pytdbot/types/buttons/inline_keyboard.py
pytdbot/types/buttons/remove_keyboard.py
pytdbot/types/buttons/show_keyboard.py
pytdbot/types/inputfile/__init__.py
pytdbot/types/inputfile/base.py
pytdbot/types/inputfile/input_file_generated.py
pytdbot/types/inputfile/input_file_id.py
pytdbot/types/inputfile/input_file_local.py
pytdbot/types/inputfile/input_file_remote.py
pytdbot/types/inputfile/input_thumbnail.py
pytdbot/types/logstream/__init__.py
pytdbot/types/logstream/base.py
pytdbot/types/logstream/log_stream_default.py
pytdbot/types/logstream/log_stream_empty.py
pytdbot/types/logstream/log_stream_file.py
pytdbot/types/plugins/__init__.py
pytdbot/types/plugins/plugins.py
pytdbot/types/response/__init__.py
pytdbot/types/response/response.py
pytdbot/types/update/__init__.py
pytdbot/types/update/update.py
Pytdbot-0.7.3.dist-info/LICENSE
Pytdbot-0.7.3.dist-info/METADATA
Pytdbot-0.7.3.dist-info/WHEEL
Pytdbot-0.7.3.dist-info/top_level.txt
Pytdbot-0.7.3.dist-info/RECORD
