Metadata-Version: 2.1
Name: Pytdbot
Version: 0.7.3
Summary: Easy-to-use asynchronous TDLib wrapper for Telegram bots.
Home-page: https://github.com/pytdbot/client
Author: AYMEN Mohammed
Author-email: let.me.code.safe@gmail.com
License: MIT
Project-URL: Source, https://github.com/pytdbot/client
Project-URL: Tracker, https://github.com/pytdbot/client/issues
Keywords: telegram,tdlib,bot,telegram-client,telegram-bot,bot-api
Platform: UNKNOWN
Requires-Python: >=3.9
License-File: LICENSE
Requires-Dist: deepdiff
